{
    "?xml": {
        "@_version": 1,
        "@_encoding": "utf-8"
    },
    "RDF": {
        "ebook": {
            "publisher": "Project Gutenberg",
            "license": {
                "@_resource": "license"
            },
            "issued": {
                "#text": "2004-02-01",
                "@_datatype": "http://www.w3.org/2001/XMLSchema#date"
            },
            "rights": "Public domain in the USA.",
            "downloads": {
                "#text": 31,
                "@_datatype": "http://www.w3.org/2001/XMLSchema#integer"
            },
            "creator": {
                "agent": {
                    "name": "Nye, Bill",
                    "birthdate": {
                        "#text": 1850,
                        "@_datatype": "http://www.w3.org/2001/XMLSchema#integer"
                    },
                    "deathdate": {
                        "#text": 1896,
                        "@_datatype": "http://www.w3.org/2001/XMLSchema#integer"
                    },
                    "alias": [
                        "Nye, Edgar Wilson",
                        "Nye, Edgar W. (Edgar Wilson)"
                    ],
                    "webpage": {
                        "@_resource": "https://en.wikipedia.org/wiki/Edgar_Wilson_Nye"
                    },
                    "@_about": "2009/agents/2704"
                }
            },
            "title": "Comic History of England",
            "language": {
                "Description": {
                    "value": {
                        "#text": "en",
                        "@_datatype": "http://purl.org/dc/terms/RFC4646"
                    },
                    "@_nodeID": "Ndb66721faf024ce9b5723073a26b2a57"
                }
            },
            "subject": [
                {
                    "Description": {
                        "memberOf": {
                            "@_resource": "http://purl.org/dc/terms/LCSH"
                        },
                        "value": "Great Britain -- History -- Humor",
                        "@_nodeID": "Nb7bd6c83c33149429e11913d7882605c"
                    }
                },
                {
                    "Description": {
                        "memberOf": {
                            "@_resource": "http://purl.org/dc/terms/LCC"
                        },
                        "value": "DA",
                        "@_nodeID": "Nc6737ed4537f41528ccccf12eebf38a3"
                    }
                }
            ],
            "bookshelf": [
                {
                    "Description": {
                        "memberOf": {
                            "@_resource": "2009/pgterms/Bookshelf"
                        },
                        "value": "Humor",
                        "@_nodeID": "N0cd80abe83af428f87d0e7ef33f7d759"
                    }
                },
                {
                    "Description": {
                        "memberOf": {
                            "@_resource": "2009/pgterms/Bookshelf"
                        },
                        "value": "United Kingdom",
                        "@_nodeID": "N73ee3d3e1ca64bd5adb9cabcd20697bb"
                    }
                }
            ],
            "hasFormat": [
                {
                    "file": {
                        "isFormatOf": {
                            "@_resource": "ebooks/11138"
                        },
                        "extent": {
                            "#text": 199370,
                            "@_datatype": "http://www.w3.org/2001/XMLSchema#integer"
                        },
                        "modified": {
                            "#text": "2022-09-05T11:51:22.222431",
                            "@_datatype": "http://www.w3.org/2001/XMLSchema#dateTime"
                        },
                        "format": {
                            "Description": {
                                "memberOf": {
                                    "@_resource": "http://purl.org/dc/terms/IMT"
                                },
                                "value": {
                                    "#text": "text/html",
                                    "@_datatype": "http://purl.org/dc/terms/IMT"
                                },
                                "@_nodeID": "N83918808aa1341afa037b956b020c344"
                            }
                        },
                        "@_about": "https://www.gutenberg.org/ebooks/11138.html.images"
                    }
                },
                {
                    "file": {
                        "isFormatOf": {
                            "@_resource": "ebooks/11138"
                        },
                        "extent": {
                            "#text": 199363,
                            "@_datatype": "http://www.w3.org/2001/XMLSchema#integer"
                        },
                        "modified": {
                            "#text": "2022-09-05T11:51:22.382435",
                            "@_datatype": "http://www.w3.org/2001/XMLSchema#dateTime"
                        },
                        "format": {
                            "Description": {
                                "memberOf": {
                                    "@_resource": "http://purl.org/dc/terms/IMT"
                                },
                                "value": {
                                    "#text": "text/html",
                                    "@_datatype": "http://purl.org/dc/terms/IMT"
                                },
                                "@_nodeID": "Nbcbf3fe6c6cc4325b3a8c3f60bacfd9d"
                            }
                        },
                        "@_about": "https://www.gutenberg.org/ebooks/11138.html.noimages"
                    }
                },
                {
                    "file": {
                        "isFormatOf": {
                            "@_resource": "ebooks/11138"
                        },
                        "extent": {
                            "#text": 127621,
                            "@_datatype": "http://www.w3.org/2001/XMLSchema#integer"
                        },
                        "modified": {
                            "#text": "2022-09-05T11:51:26.585460",
                            "@_datatype": "http://www.w3.org/2001/XMLSchema#dateTime"
                        },
                        "format": {
                            "Description": {
                                "memberOf": {
                                    "@_resource": "http://purl.org/dc/terms/IMT"
                                },
                                "value": {
                                    "#text": "application/epub+zip",
                                    "@_datatype": "http://purl.org/dc/terms/IMT"
                                },
                                "@_nodeID": "Ncaca7dd0c189439db9d54805227f80b3"
                            }
                        },
                        "@_about": "https://www.gutenberg.org/ebooks/11138.epub.images"
                    }
                },
                {
                    "file": {
                        "isFormatOf": {
                            "@_resource": "ebooks/11138"
                        },
                        "extent": {
                            "#text": 127620,
                            "@_datatype": "http://www.w3.org/2001/XMLSchema#integer"
                        },
                        "modified": {
                            "#text": "2022-09-05T11:51:22.938431",
                            "@_datatype": "http://www.w3.org/2001/XMLSchema#dateTime"
                        },
                        "format": {
                            "Description": {
                                "memberOf": {
                                    "@_resource": "http://purl.org/dc/terms/IMT"
                                },
                                "value": {
                                    "#text": "application/epub+zip",
                                    "@_datatype": "http://purl.org/dc/terms/IMT"
                                },
                                "@_nodeID": "Neb969933cd39446e97fb1b89b5c12105"
                            }
                        },
                        "@_about": "https://www.gutenberg.org/ebooks/11138.epub.noimages"
                    }
                },
                {
                    "file": {
                        "isFormatOf": {
                            "@_resource": "ebooks/11138"
                        },
                        "extent": {
                            "#text": 227880,
                            "@_datatype": "http://www.w3.org/2001/XMLSchema#integer"
                        },
                        "modified": {
                            "#text": "2022-09-05T11:51:29.459494",
                            "@_datatype": "http://www.w3.org/2001/XMLSchema#dateTime"
                        },
                        "format": {
                            "Description": {
                                "memberOf": {
                                    "@_resource": "http://purl.org/dc/terms/IMT"
                                },
                                "value": {
                                    "#text": "application/x-mobipocket-ebook",
                                    "@_datatype": "http://purl.org/dc/terms/IMT"
                                },
                                "@_nodeID": "N46727bf97d754fa38aa1b3e47f08360b"
                            }
                        },
                        "@_about": "https://www.gutenberg.org/ebooks/11138.kindle.images"
                    }
                },
                {
                    "file": {
                        "isFormatOf": {
                            "@_resource": "ebooks/11138"
                        },
                        "extent": {
                            "#text": 227880,
                            "@_datatype": "http://www.w3.org/2001/XMLSchema#integer"
                        },
                        "modified": {
                            "#text": "2022-09-05T11:51:25.814459",
                            "@_datatype": "http://www.w3.org/2001/XMLSchema#dateTime"
                        },
                        "format": {
                            "Description": {
                                "memberOf": {
                                    "@_resource": "http://purl.org/dc/terms/IMT"
                                },
                                "value": {
                                    "#text": "application/x-mobipocket-ebook",
                                    "@_datatype": "http://purl.org/dc/terms/IMT"
                                },
                                "@_nodeID": "N67a672b1ae30451fb499c11be55fd0ea"
                            }
                        },
                        "@_about": "https://www.gutenberg.org/ebooks/11138.kindle.noimages"
                    }
                },
                {
                    "file": {
                        "isFormatOf": {
                            "@_resource": "ebooks/11138"
                        },
                        "extent": {
                            "#text": 123268,
                            "@_datatype": "http://www.w3.org/2001/XMLSchema#integer"
                        },
                        "modified": {
                            "#text": "2022-09-05T11:51:29.912484",
                            "@_datatype": "http://www.w3.org/2001/XMLSchema#dateTime"
                        },
                        "format": {
                            "Description": {
                                "memberOf": {
                                    "@_resource": "http://purl.org/dc/terms/IMT"
                                },
                                "value": {
                                    "#text": "application/epub+zip",
                                    "@_datatype": "http://purl.org/dc/terms/IMT"
                                },
                                "@_nodeID": "Nfda45bb52a114237953bef2ac154c049"
                            }
                        },
                        "@_about": "https://www.gutenberg.org/ebooks/11138.epub3.images"
                    }
                },
                {
                    "file": {
                        "isFormatOf": {
                            "@_resource": "ebooks/11138"
                        },
                        "extent": {
                            "#text": 240148,
                            "@_datatype": "http://www.w3.org/2001/XMLSchema#integer"
                        },
                        "modified": {
                            "#text": "2022-09-05T11:51:32.396516",
                            "@_datatype": "http://www.w3.org/2001/XMLSchema#dateTime"
                        },
                        "format": {
                            "Description": {
                                "memberOf": {
                                    "@_resource": "http://purl.org/dc/terms/IMT"
                                },
                                "value": {
                                    "#text": "application/x-mobipocket-ebook",
                                    "@_datatype": "http://purl.org/dc/terms/IMT"
                                },
                                "@_nodeID": "Nc1df4b15810449379019d1530f21bd20"
                            }
                        },
                        "@_about": "https://www.gutenberg.org/ebooks/11138.kf8.images"
                    }
                },
                {
                    "file": {
                        "isFormatOf": {
                            "@_resource": "ebooks/11138"
                        },
                        "extent": {
                            "#text": 176543,
                            "@_datatype": "http://www.w3.org/2001/XMLSchema#integer"
                        },
                        "modified": {
                            "#text": "2022-09-05T11:51:21.994426",
                            "@_datatype": "http://www.w3.org/2001/XMLSchema#dateTime"
                        },
                        "format": {
                            "Description": {
                                "memberOf": {
                                    "@_resource": "http://purl.org/dc/terms/IMT"
                                },
                                "value": {
                                    "#text": "text/plain",
                                    "@_datatype": "http://purl.org/dc/terms/IMT"
                                },
                                "@_nodeID": "N88ea88eb8df84985b6db376e30f3cc1b"
                            }
                        },
                        "@_about": "https://www.gutenberg.org/ebooks/11138.txt.utf-8"
                    }
                },
                {
                    "file": {
                        "isFormatOf": {
                            "@_resource": "ebooks/11138"
                        },
                        "extent": {
                            "#text": 176542,
                            "@_datatype": "http://www.w3.org/2001/XMLSchema#integer"
                        },
                        "modified": {
                            "#text": "2004-02-18T07:35:26",
                            "@_datatype": "http://www.w3.org/2001/XMLSchema#dateTime"
                        },
                        "format": {
                            "Description": {
                                "memberOf": {
                                    "@_resource": "http://purl.org/dc/terms/IMT"
                                },
                                "value": {
                                    "#text": "text/plain; charset=iso-8859-1",
                                    "@_datatype": "http://purl.org/dc/terms/IMT"
                                },
                                "@_nodeID": "Nb59e81ccd8ea4d208a1f224825ccf039"
                            }
                        },
                        "@_about": "https://www.gutenberg.org/files/11138/11138-8.txt"
                    }
                },
                {
                    "file": {
                        "isFormatOf": {
                            "@_resource": "ebooks/11138"
                        },
                        "extent": {
                            "#text": 71310,
                            "@_datatype": "http://www.w3.org/2001/XMLSchema#integer"
                        },
                        "modified": {
                            "#text": "2004-02-18T07:35:26",
                            "@_datatype": "http://www.w3.org/2001/XMLSchema#dateTime"
                        },
                        "format": [
                            {
                                "Description": {
                                    "memberOf": {
                                        "@_resource": "http://purl.org/dc/terms/IMT"
                                    },
                                    "value": {
                                        "#text": "text/plain; charset=iso-8859-1",
                                        "@_datatype": "http://purl.org/dc/terms/IMT"
                                    },
                                    "@_nodeID": "N1039b18b35864c39b3b78a4545870754"
                                }
                            },
                            {
                                "Description": {
                                    "memberOf": {
                                        "@_resource": "http://purl.org/dc/terms/IMT"
                                    },
                                    "value": {
                                        "#text": "application/zip",
                                        "@_datatype": "http://purl.org/dc/terms/IMT"
                                    },
                                    "@_nodeID": "N72db54fd8f234d20970af6995fc2df59"
                                }
                            }
                        ],
                        "@_about": "https://www.gutenberg.org/files/11138/11138-8.zip"
                    }
                },
                {
                    "file": {
                        "isFormatOf": {
                            "@_resource": "ebooks/11138"
                        },
                        "extent": {
                            "#text": 176533,
                            "@_datatype": "http://www.w3.org/2001/XMLSchema#integer"
                        },
                        "modified": {
                            "#text": "2004-02-18T07:35:26",
                            "@_datatype": "http://www.w3.org/2001/XMLSchema#dateTime"
                        },
                        "format": {
                            "Description": {
                                "memberOf": {
                                    "@_resource": "http://purl.org/dc/terms/IMT"
                                },
                                "value": {
                                    "#text": "text/plain; charset=us-ascii",
                                    "@_datatype": "http://purl.org/dc/terms/IMT"
                                },
                                "@_nodeID": "N2d68bd9706474d6a9ea3bb96fccde45c"
                            }
                        },
                        "@_about": "https://www.gutenberg.org/files/11138/11138.txt"
                    }
                },
                {
                    "file": {
                        "isFormatOf": {
                            "@_resource": "ebooks/11138"
                        },
                        "extent": {
                            "#text": 71259,
                            "@_datatype": "http://www.w3.org/2001/XMLSchema#integer"
                        },
                        "modified": {
                            "#text": "2004-02-18T07:35:26",
                            "@_datatype": "http://www.w3.org/2001/XMLSchema#dateTime"
                        },
                        "format": [
                            {
                                "Description": {
                                    "memberOf": {
                                        "@_resource": "http://purl.org/dc/terms/IMT"
                                    },
                                    "value": {
                                        "#text": "text/plain",
                                        "@_datatype": "http://purl.org/dc/terms/IMT"
                                    },
                                    "@_nodeID": "Nfe2bf353dee243f687cbd14329d537eb"
                                }
                            },
                            {
                                "Description": {
                                    "memberOf": {
                                        "@_resource": "http://purl.org/dc/terms/IMT"
                                    },
                                    "value": {
                                        "#text": "application/zip",
                                        "@_datatype": "http://purl.org/dc/terms/IMT"
                                    },
                                    "@_nodeID": "N0670f0cc767840f4ae70f49318d698e6"
                                }
                            }
                        ],
                        "@_about": "https://www.gutenberg.org/files/11138/11138.zip"
                    }
                },
                {
                    "file": {
                        "isFormatOf": {
                            "@_resource": "ebooks/11138"
                        },
                        "extent": {
                            "#text": 14672,
                            "@_datatype": "http://www.w3.org/2001/XMLSchema#integer"
                        },
                        "modified": {
                            "#text": "2022-09-05T11:51:32.526503",
                            "@_datatype": "http://www.w3.org/2001/XMLSchema#dateTime"
                        },
                        "format": {
                            "Description": {
                                "memberOf": {
                                    "@_resource": "http://purl.org/dc/terms/IMT"
                                },
                                "value": {
                                    "#text": "application/rdf+xml",
                                    "@_datatype": "http://purl.org/dc/terms/IMT"
                                },
                                "@_nodeID": "N2cfdaaab6c974eefafc08e394966ccfd"
                            }
                        },
                        "@_about": "https://www.gutenberg.org/ebooks/11138.rdf"
                    }
                },
                {
                    "file": {
                        "isFormatOf": {
                            "@_resource": "ebooks/11138"
                        },
                        "extent": {
                            "#text": 13764,
                            "@_datatype": "http://www.w3.org/2001/XMLSchema#integer"
                        },
                        "modified": {
                            "#text": "2022-09-05T11:51:26.180447",
                            "@_datatype": "http://www.w3.org/2001/XMLSchema#dateTime"
                        },
                        "format": {
                            "Description": {
                                "memberOf": {
                                    "@_resource": "http://purl.org/dc/terms/IMT"
                                },
                                "value": {
                                    "#text": "image/jpeg",
                                    "@_datatype": "http://purl.org/dc/terms/IMT"
                                },
                                "@_nodeID": "N9a4986faee3d406cb671cfb7129fcd35"
                            }
                        },
                        "@_about": "https://www.gutenberg.org/cache/epub/11138/pg11138.cover.medium.jpg"
                    }
                },
                {
                    "file": {
                        "isFormatOf": {
                            "@_resource": "ebooks/11138"
                        },
                        "extent": {
                            "#text": 3845,
                            "@_datatype": "http://www.w3.org/2001/XMLSchema#integer"
                        },
                        "modified": {
                            "#text": "2022-09-05T11:51:26.016457",
                            "@_datatype": "http://www.w3.org/2001/XMLSchema#dateTime"
                        },
                        "format": {
                            "Description": {
                                "memberOf": {
                                    "@_resource": "http://purl.org/dc/terms/IMT"
                                },
                                "value": {
                                    "#text": "image/jpeg",
                                    "@_datatype": "http://purl.org/dc/terms/IMT"
                                },
                                "@_nodeID": "N7a99bc071527463d900d1b10cfb45f3d"
                            }
                        },
                        "@_about": "https://www.gutenberg.org/cache/epub/11138/pg11138.cover.small.jpg"
                    }
                }
            ],
            "@_about": "ebooks/11138"
        },
        "Work": {
            "license": {
                "@_resource": "https://creativecommons.org/publicdomain/zero/1.0/"
            },
            "comment": "Archives containing the RDF files for *all* our books can be downloaded at\n            https://www.gutenberg.org/wiki/Gutenberg:Feeds#The_Complete_Project_Gutenberg_Catalog",
            "@_about": ""
        },
        "Description": {
            "description": "en.wikipedia",
            "@_about": "https://en.wikipedia.org/wiki/Edgar_Wilson_Nye"
        },
        "@_base": "http://www.gutenberg.org/"
    }
}
