{
    "?xml": {
        "@_version": 1,
        "@_encoding": "utf-8"
    },
    "RDF": {
        "ebook": {
            "publisher": "Project Gutenberg",
            "license": {
                "@_resource": "license"
            },
            "issued": {
                "#text": "2004-02-01",
                "@_datatype": "http://www.w3.org/2001/XMLSchema#date"
            },
            "rights": "Public domain in the USA.",
            "downloads": {
                "#text": 49,
                "@_datatype": "http://www.w3.org/2001/XMLSchema#integer"
            },
            "creator": {
                "agent": {
                    "name": "Anonymous",
                    "alias": "Anonyme",
                    "webpage": [
                        {
                            "@_resource": "https://en.wikipedia.org/wiki/Anonymous_work"
                        },
                        {
                            "@_resource": "ebooks/author/49"
                        }
                    ],
                    "@_about": "2009/agents/216"
                }
            },
            "title": "The World Turned Upside Down&#13;\nOr, No News, and Strange News",
            "language": {
                "Description": {
                    "value": {
                        "#text": "en",
                        "@_datatype": "http://purl.org/dc/terms/RFC4646"
                    },
                    "@_nodeID": "Naab798af1cc143d885167db61213daa7"
                }
            },
            "subject": [
                {
                    "Description": {
                        "memberOf": {
                            "@_resource": "http://purl.org/dc/terms/LCSH"
                        },
                        "value": "Children's poetry",
                        "@_nodeID": "Ndbbd49c857e243cbbf62b8f1a6a3239d"
                    }
                },
                {
                    "Description": {
                        "memberOf": {
                            "@_resource": "http://purl.org/dc/terms/LCSH"
                        },
                        "value": "Picture books for children",
                        "@_nodeID": "N04914dc6e5b0456096647491e9177b57"
                    }
                },
                {
                    "Description": {
                        "memberOf": {
                            "@_resource": "http://purl.org/dc/terms/LCC"
                        },
                        "value": "PZ",
                        "@_nodeID": "Ne54765b0e5c04cf1810f56b6a5613365"
                    }
                }
            ],
            "bookshelf": {
                "Description": {
                    "memberOf": {
                        "@_resource": "2009/pgterms/Bookshelf"
                    },
                    "value": "Children's Picture Books",
                    "@_nodeID": "N6d3177353c304efebc9d89f896f5a2d8"
                }
            },
            "hasFormat": [
                {
                    "file": {
                        "isFormatOf": {
                            "@_resource": "ebooks/10965"
                        },
                        "extent": {
                            "#text": 36659,
                            "@_datatype": "http://www.w3.org/2001/XMLSchema#integer"
                        },
                        "modified": {
                            "#text": "2004-02-06T21:08:34",
                            "@_datatype": "http://www.w3.org/2001/XMLSchema#dateTime"
                        },
                        "format": {
                            "Description": {
                                "memberOf": {
                                    "@_resource": "http://purl.org/dc/terms/IMT"
                                },
                                "value": {
                                    "#text": "text/html; charset=iso-8859-1",
                                    "@_datatype": "http://purl.org/dc/terms/IMT"
                                },
                                "@_nodeID": "Nba4e23fc908543468d34b5f570b56857"
                            }
                        },
                        "@_about": "https://www.gutenberg.org/files/10965/10965-h/10965-h.htm"
                    }
                },
                {
                    "file": {
                        "isFormatOf": {
                            "@_resource": "ebooks/10965"
                        },
                        "extent": {
                            "#text": 294833,
                            "@_datatype": "http://www.w3.org/2001/XMLSchema#integer"
                        },
                        "modified": {
                            "#text": "2004-02-06T21:08:56",
                            "@_datatype": "http://www.w3.org/2001/XMLSchema#dateTime"
                        },
                        "format": [
                            {
                                "Description": {
                                    "memberOf": {
                                        "@_resource": "http://purl.org/dc/terms/IMT"
                                    },
                                    "value": {
                                        "#text": "text/html",
                                        "@_datatype": "http://purl.org/dc/terms/IMT"
                                    },
                                    "@_nodeID": "N4c23d5fd1b684792af5e0d278929086e"
                                }
                            },
                            {
                                "Description": {
                                    "memberOf": {
                                        "@_resource": "http://purl.org/dc/terms/IMT"
                                    },
                                    "value": {
                                        "#text": "application/zip",
                                        "@_datatype": "http://purl.org/dc/terms/IMT"
                                    },
                                    "@_nodeID": "Nd80b31f93e0d4276ba5defae3df037d7"
                                }
                            }
                        ],
                        "@_about": "https://www.gutenberg.org/files/10965/10965-h.zip"
                    }
                },
                {
                    "file": {
                        "isFormatOf": {
                            "@_resource": "ebooks/10965"
                        },
                        "extent": {
                            "#text": 41090,
                            "@_datatype": "http://www.w3.org/2001/XMLSchema#integer"
                        },
                        "modified": {
                            "#text": "2022-09-05T11:00:27.456424",
                            "@_datatype": "http://www.w3.org/2001/XMLSchema#dateTime"
                        },
                        "format": {
                            "Description": {
                                "memberOf": {
                                    "@_resource": "http://purl.org/dc/terms/IMT"
                                },
                                "value": {
                                    "#text": "text/html",
                                    "@_datatype": "http://purl.org/dc/terms/IMT"
                                },
                                "@_nodeID": "Nea48718160724e56a2a2eb367a5e950a"
                            }
                        },
                        "@_about": "https://www.gutenberg.org/ebooks/10965.html.images"
                    }
                },
                {
                    "file": {
                        "isFormatOf": {
                            "@_resource": "ebooks/10965"
                        },
                        "extent": {
                            "#text": 353167,
                            "@_datatype": "http://www.w3.org/2001/XMLSchema#integer"
                        },
                        "modified": {
                            "#text": "2022-09-05T11:00:30.364431",
                            "@_datatype": "http://www.w3.org/2001/XMLSchema#dateTime"
                        },
                        "format": {
                            "Description": {
                                "memberOf": {
                                    "@_resource": "http://purl.org/dc/terms/IMT"
                                },
                                "value": {
                                    "#text": "application/epub+zip",
                                    "@_datatype": "http://purl.org/dc/terms/IMT"
                                },
                                "@_nodeID": "Na225e180c7b54d49bd167c8e314512cd"
                            }
                        },
                        "@_about": "https://www.gutenberg.org/ebooks/10965.epub.images"
                    }
                },
                {
                    "file": {
                        "isFormatOf": {
                            "@_resource": "ebooks/10965"
                        },
                        "extent": {
                            "#text": 72641,
                            "@_datatype": "http://www.w3.org/2001/XMLSchema#integer"
                        },
                        "modified": {
                            "#text": "2022-09-05T11:00:27.852446",
                            "@_datatype": "http://www.w3.org/2001/XMLSchema#dateTime"
                        },
                        "format": {
                            "Description": {
                                "memberOf": {
                                    "@_resource": "http://purl.org/dc/terms/IMT"
                                },
                                "value": {
                                    "#text": "application/epub+zip",
                                    "@_datatype": "http://purl.org/dc/terms/IMT"
                                },
                                "@_nodeID": "N5cacdafd1c684514b11a12073c3d8c7f"
                            }
                        },
                        "@_about": "https://www.gutenberg.org/ebooks/10965.epub.noimages"
                    }
                },
                {
                    "file": {
                        "isFormatOf": {
                            "@_resource": "ebooks/10965"
                        },
                        "extent": {
                            "#text": 1938570,
                            "@_datatype": "http://www.w3.org/2001/XMLSchema#integer"
                        },
                        "modified": {
                            "#text": "2022-09-05T11:00:31.965455",
                            "@_datatype": "http://www.w3.org/2001/XMLSchema#dateTime"
                        },
                        "format": {
                            "Description": {
                                "memberOf": {
                                    "@_resource": "http://purl.org/dc/terms/IMT"
                                },
                                "value": {
                                    "#text": "application/x-mobipocket-ebook",
                                    "@_datatype": "http://purl.org/dc/terms/IMT"
                                },
                                "@_nodeID": "N931dd53b43ac413d993f35e69eac5a62"
                            }
                        },
                        "@_about": "https://www.gutenberg.org/ebooks/10965.kindle.images"
                    }
                },
                {
                    "file": {
                        "isFormatOf": {
                            "@_resource": "ebooks/10965"
                        },
                        "extent": {
                            "#text": 176767,
                            "@_datatype": "http://www.w3.org/2001/XMLSchema#integer"
                        },
                        "modified": {
                            "#text": "2022-09-05T11:00:29.311422",
                            "@_datatype": "http://www.w3.org/2001/XMLSchema#dateTime"
                        },
                        "format": {
                            "Description": {
                                "memberOf": {
                                    "@_resource": "http://purl.org/dc/terms/IMT"
                                },
                                "value": {
                                    "#text": "application/x-mobipocket-ebook",
                                    "@_datatype": "http://purl.org/dc/terms/IMT"
                                },
                                "@_nodeID": "N64ed3832e3f74c2893f1dc077b3fde8f"
                            }
                        },
                        "@_about": "https://www.gutenberg.org/ebooks/10965.kindle.noimages"
                    }
                },
                {
                    "file": {
                        "isFormatOf": {
                            "@_resource": "ebooks/10965"
                        },
                        "extent": {
                            "#text": 353116,
                            "@_datatype": "http://www.w3.org/2001/XMLSchema#integer"
                        },
                        "modified": {
                            "#text": "2022-09-05T11:00:32.691527",
                            "@_datatype": "http://www.w3.org/2001/XMLSchema#dateTime"
                        },
                        "format": {
                            "Description": {
                                "memberOf": {
                                    "@_resource": "http://purl.org/dc/terms/IMT"
                                },
                                "value": {
                                    "#text": "application/epub+zip",
                                    "@_datatype": "http://purl.org/dc/terms/IMT"
                                },
                                "@_nodeID": "Ndd02fc888b38459b9f2e0683ea97dc64"
                            }
                        },
                        "@_about": "https://www.gutenberg.org/ebooks/10965.epub3.images"
                    }
                },
                {
                    "file": {
                        "isFormatOf": {
                            "@_resource": "ebooks/10965"
                        },
                        "extent": {
                            "#text": 1948674,
                            "@_datatype": "http://www.w3.org/2001/XMLSchema#integer"
                        },
                        "modified": {
                            "#text": "2022-09-05T11:00:34.250484",
                            "@_datatype": "http://www.w3.org/2001/XMLSchema#dateTime"
                        },
                        "format": {
                            "Description": {
                                "memberOf": {
                                    "@_resource": "http://purl.org/dc/terms/IMT"
                                },
                                "value": {
                                    "#text": "application/x-mobipocket-ebook",
                                    "@_datatype": "http://purl.org/dc/terms/IMT"
                                },
                                "@_nodeID": "Nc1c44055ca3f4828927c77d3ca772a70"
                            }
                        },
                        "@_about": "https://www.gutenberg.org/ebooks/10965.kf8.images"
                    }
                },
                {
                    "file": {
                        "isFormatOf": {
                            "@_resource": "ebooks/10965"
                        },
                        "extent": {
                            "#text": 30401,
                            "@_datatype": "http://www.w3.org/2001/XMLSchema#integer"
                        },
                        "modified": {
                            "#text": "2022-09-05T11:00:27.213417",
                            "@_datatype": "http://www.w3.org/2001/XMLSchema#dateTime"
                        },
                        "format": {
                            "Description": {
                                "memberOf": {
                                    "@_resource": "http://purl.org/dc/terms/IMT"
                                },
                                "value": {
                                    "#text": "text/plain",
                                    "@_datatype": "http://purl.org/dc/terms/IMT"
                                },
                                "@_nodeID": "N4e4456a9134f4c2d88e330380efe9421"
                            }
                        },
                        "@_about": "https://www.gutenberg.org/ebooks/10965.txt.utf-8"
                    }
                },
                {
                    "file": {
                        "isFormatOf": {
                            "@_resource": "ebooks/10965"
                        },
                        "extent": {
                            "#text": 30418,
                            "@_datatype": "http://www.w3.org/2001/XMLSchema#integer"
                        },
                        "modified": {
                            "#text": "2004-02-06T21:04:28",
                            "@_datatype": "http://www.w3.org/2001/XMLSchema#dateTime"
                        },
                        "format": {
                            "Description": {
                                "memberOf": {
                                    "@_resource": "http://purl.org/dc/terms/IMT"
                                },
                                "value": {
                                    "#text": "text/plain; charset=us-ascii",
                                    "@_datatype": "http://purl.org/dc/terms/IMT"
                                },
                                "@_nodeID": "N79a04a5e665e4a6d93b95ae7d0ddcd90"
                            }
                        },
                        "@_about": "https://www.gutenberg.org/files/10965/10965.txt"
                    }
                },
                {
                    "file": {
                        "isFormatOf": {
                            "@_resource": "ebooks/10965"
                        },
                        "extent": {
                            "#text": 10486,
                            "@_datatype": "http://www.w3.org/2001/XMLSchema#integer"
                        },
                        "modified": {
                            "#text": "2004-02-06T21:08:54",
                            "@_datatype": "http://www.w3.org/2001/XMLSchema#dateTime"
                        },
                        "format": [
                            {
                                "Description": {
                                    "memberOf": {
                                        "@_resource": "http://purl.org/dc/terms/IMT"
                                    },
                                    "value": {
                                        "#text": "text/plain",
                                        "@_datatype": "http://purl.org/dc/terms/IMT"
                                    },
                                    "@_nodeID": "Nb0ad631d6ff041eb9e455df9abce44eb"
                                }
                            },
                            {
                                "Description": {
                                    "memberOf": {
                                        "@_resource": "http://purl.org/dc/terms/IMT"
                                    },
                                    "value": {
                                        "#text": "application/zip",
                                        "@_datatype": "http://purl.org/dc/terms/IMT"
                                    },
                                    "@_nodeID": "N412bc3f5871f415fb58aa26c31effdcc"
                                }
                            }
                        ],
                        "@_about": "https://www.gutenberg.org/files/10965/10965.zip"
                    }
                },
                {
                    "file": {
                        "isFormatOf": {
                            "@_resource": "ebooks/10965"
                        },
                        "extent": {
                            "#text": 13850,
                            "@_datatype": "http://www.w3.org/2001/XMLSchema#integer"
                        },
                        "modified": {
                            "#text": "2022-09-05T11:00:34.388478",
                            "@_datatype": "http://www.w3.org/2001/XMLSchema#dateTime"
                        },
                        "format": {
                            "Description": {
                                "memberOf": {
                                    "@_resource": "http://purl.org/dc/terms/IMT"
                                },
                                "value": {
                                    "#text": "application/rdf+xml",
                                    "@_datatype": "http://purl.org/dc/terms/IMT"
                                },
                                "@_nodeID": "N4f20058774974ded9cbf8aa4f005384e"
                            }
                        },
                        "@_about": "https://www.gutenberg.org/ebooks/10965.rdf"
                    }
                },
                {
                    "file": {
                        "isFormatOf": {
                            "@_resource": "ebooks/10965"
                        },
                        "extent": {
                            "#text": 17258,
                            "@_datatype": "http://www.w3.org/2001/XMLSchema#integer"
                        },
                        "modified": {
                            "#text": "2022-09-05T11:00:29.680426",
                            "@_datatype": "http://www.w3.org/2001/XMLSchema#dateTime"
                        },
                        "format": {
                            "Description": {
                                "memberOf": {
                                    "@_resource": "http://purl.org/dc/terms/IMT"
                                },
                                "value": {
                                    "#text": "image/jpeg",
                                    "@_datatype": "http://purl.org/dc/terms/IMT"
                                },
                                "@_nodeID": "N1cd4a933b6334a81859eec54d16e2d23"
                            }
                        },
                        "@_about": "https://www.gutenberg.org/cache/epub/10965/pg10965.cover.medium.jpg"
                    }
                },
                {
                    "file": {
                        "isFormatOf": {
                            "@_resource": "ebooks/10965"
                        },
                        "extent": {
                            "#text": 4050,
                            "@_datatype": "http://www.w3.org/2001/XMLSchema#integer"
                        },
                        "modified": {
                            "#text": "2022-09-05T11:00:29.513441",
                            "@_datatype": "http://www.w3.org/2001/XMLSchema#dateTime"
                        },
                        "format": {
                            "Description": {
                                "memberOf": {
                                    "@_resource": "http://purl.org/dc/terms/IMT"
                                },
                                "value": {
                                    "#text": "image/jpeg",
                                    "@_datatype": "http://purl.org/dc/terms/IMT"
                                },
                                "@_nodeID": "N946508f5f6744cf0a25a2675167bf3d2"
                            }
                        },
                        "@_about": "https://www.gutenberg.org/cache/epub/10965/pg10965.cover.small.jpg"
                    }
                }
            ],
            "@_about": "ebooks/10965"
        },
        "Work": {
            "license": {
                "@_resource": "https://creativecommons.org/publicdomain/zero/1.0/"
            },
            "comment": "Archives containing the RDF files for *all* our books can be downloaded at\n            https://www.gutenberg.org/wiki/Gutenberg:Feeds#The_Complete_Project_Gutenberg_Catalog",
            "@_about": ""
        },
        "Description": [
            {
                "description": "More titles under Unknown",
                "@_about": "ebooks/author/49"
            },
            {
                "description": "en.wikipedia",
                "@_about": "https://en.wikipedia.org/wiki/Anonymous_work"
            }
        ],
        "@_base": "http://www.gutenberg.org/"
    }
}
