{
    "?xml": {
        "@_version": 1,
        "@_encoding": "utf-8"
    },
    "RDF": {
        "Work": {
            "license": {
                "@_resource": "https://creativecommons.org/publicdomain/zero/1.0/"
            },
            "comment": "Archives containing the RDF files for *all* our books can be downloaded at\n            https://www.gutenberg.org/wiki/Gutenberg:Feeds#The_Complete_Project_Gutenberg_Catalog",
            "@_about": ""
        },
        "ebook": {
            "publisher": "Project Gutenberg",
            "license": {
                "@_resource": "license"
            },
            "issued": {
                "#text": "2004-02-01",
                "@_datatype": "http://www.w3.org/2001/XMLSchema#date"
            },
            "rights": "Public domain in the USA.",
            "downloads": {
                "#text": 60,
                "@_datatype": "http://www.w3.org/2001/XMLSchema#integer"
            },
            "creator": {
                "agent": {
                    "name": "Anonymous",
                    "alias": "Anonyme",
                    "webpage": [
                        {
                            "@_resource": "https://en.wikipedia.org/wiki/Anonymous_work"
                        },
                        {
                            "@_resource": "ebooks/author/49"
                        }
                    ],
                    "@_about": "2009/agents/216"
                }
            },
            "title": "Aunt Mary's Primer&#13;\nAdorned with a Hundred and Twenty Pretty Pictures",
            "language": {
                "Description": {
                    "value": {
                        "#text": "en",
                        "@_datatype": "http://purl.org/dc/terms/RFC4646"
                    },
                    "@_nodeID": "Nbe58eeb86ca248568fbb91ff09ad70ec"
                }
            },
            "subject": [
                {
                    "Description": {
                        "memberOf": {
                            "@_resource": "http://purl.org/dc/terms/LCSH"
                        },
                        "value": "Readers (Primary)",
                        "@_nodeID": "N3fae5dfdcc414fb2b1e30f9eea9cf6cf"
                    }
                },
                {
                    "Description": {
                        "memberOf": {
                            "@_resource": "http://purl.org/dc/terms/LCC"
                        },
                        "value": "PE",
                        "@_nodeID": "N10eaa7a020eb4fdca50aa57e5077d694"
                    }
                }
            ],
            "bookshelf": {
                "Description": {
                    "memberOf": {
                        "@_resource": "2009/pgterms/Bookshelf"
                    },
                    "value": "Children's Picture Books",
                    "@_nodeID": "N7c5619223dbb434badcc38bc2ae0569f"
                }
            },
            "hasFormat": [
                {
                    "file": {
                        "isFormatOf": {
                            "@_resource": "ebooks/11065"
                        },
                        "extent": {
                            "#text": 41065,
                            "@_datatype": "http://www.w3.org/2001/XMLSchema#integer"
                        },
                        "modified": {
                            "#text": "2004-02-12T23:54:07",
                            "@_datatype": "http://www.w3.org/2001/XMLSchema#dateTime"
                        },
                        "format": {
                            "Description": {
                                "memberOf": {
                                    "@_resource": "http://purl.org/dc/terms/IMT"
                                },
                                "value": {
                                    "#text": "text/html; charset=us-ascii",
                                    "@_datatype": "http://purl.org/dc/terms/IMT"
                                },
                                "@_nodeID": "N437471f7f7a94b67be486c71ba79ae5f"
                            }
                        },
                        "@_about": "https://www.gutenberg.org/files/11065/11065-h/11065-h.htm"
                    }
                },
                {
                    "file": {
                        "isFormatOf": {
                            "@_resource": "ebooks/11065"
                        },
                        "extent": {
                            "#text": 1342364,
                            "@_datatype": "http://www.w3.org/2001/XMLSchema#integer"
                        },
                        "modified": {
                            "#text": "2004-02-12T23:57:58",
                            "@_datatype": "http://www.w3.org/2001/XMLSchema#dateTime"
                        },
                        "format": [
                            {
                                "Description": {
                                    "memberOf": {
                                        "@_resource": "http://purl.org/dc/terms/IMT"
                                    },
                                    "value": {
                                        "#text": "text/html",
                                        "@_datatype": "http://purl.org/dc/terms/IMT"
                                    },
                                    "@_nodeID": "N667605d94fda417484a99403932fc9de"
                                }
                            },
                            {
                                "Description": {
                                    "memberOf": {
                                        "@_resource": "http://purl.org/dc/terms/IMT"
                                    },
                                    "value": {
                                        "#text": "application/zip",
                                        "@_datatype": "http://purl.org/dc/terms/IMT"
                                    },
                                    "@_nodeID": "N69bda4302b274ae2b0e44c9d401810b0"
                                }
                            }
                        ],
                        "@_about": "https://www.gutenberg.org/files/11065/11065-h.zip"
                    }
                },
                {
                    "file": {
                        "isFormatOf": {
                            "@_resource": "ebooks/11065"
                        },
                        "extent": {
                            "#text": 45354,
                            "@_datatype": "http://www.w3.org/2001/XMLSchema#integer"
                        },
                        "modified": {
                            "#text": "2022-09-05T11:30:06.939705",
                            "@_datatype": "http://www.w3.org/2001/XMLSchema#dateTime"
                        },
                        "format": {
                            "Description": {
                                "memberOf": {
                                    "@_resource": "http://purl.org/dc/terms/IMT"
                                },
                                "value": {
                                    "#text": "text/html",
                                    "@_datatype": "http://purl.org/dc/terms/IMT"
                                },
                                "@_nodeID": "N5dc8eaf4361d439095c3f0c2e0152969"
                            }
                        },
                        "@_about": "https://www.gutenberg.org/ebooks/11065.html.images"
                    }
                },
                {
                    "file": {
                        "isFormatOf": {
                            "@_resource": "ebooks/11065"
                        },
                        "extent": {
                            "#text": 1343800,
                            "@_datatype": "http://www.w3.org/2001/XMLSchema#integer"
                        },
                        "modified": {
                            "#text": "2022-09-05T11:30:09.222727",
                            "@_datatype": "http://www.w3.org/2001/XMLSchema#dateTime"
                        },
                        "format": {
                            "Description": {
                                "memberOf": {
                                    "@_resource": "http://purl.org/dc/terms/IMT"
                                },
                                "value": {
                                    "#text": "application/epub+zip",
                                    "@_datatype": "http://purl.org/dc/terms/IMT"
                                },
                                "@_nodeID": "N489518ca93cf493084a7c3cb59b67559"
                            }
                        },
                        "@_about": "https://www.gutenberg.org/ebooks/11065.epub.images"
                    }
                },
                {
                    "file": {
                        "isFormatOf": {
                            "@_resource": "ebooks/11065"
                        },
                        "extent": {
                            "#text": 62636,
                            "@_datatype": "http://www.w3.org/2001/XMLSchema#integer"
                        },
                        "modified": {
                            "#text": "2022-09-05T11:30:07.060696",
                            "@_datatype": "http://www.w3.org/2001/XMLSchema#dateTime"
                        },
                        "format": {
                            "Description": {
                                "memberOf": {
                                    "@_resource": "http://purl.org/dc/terms/IMT"
                                },
                                "value": {
                                    "#text": "application/epub+zip",
                                    "@_datatype": "http://purl.org/dc/terms/IMT"
                                },
                                "@_nodeID": "N70f1ef2509ac4c09bcdd61d171a5174e"
                            }
                        },
                        "@_about": "https://www.gutenberg.org/ebooks/11065.epub.noimages"
                    }
                },
                {
                    "file": {
                        "isFormatOf": {
                            "@_resource": "ebooks/11065"
                        },
                        "extent": {
                            "#text": 1303895,
                            "@_datatype": "http://www.w3.org/2001/XMLSchema#integer"
                        },
                        "modified": {
                            "#text": "2022-09-05T11:30:10.758737",
                            "@_datatype": "http://www.w3.org/2001/XMLSchema#dateTime"
                        },
                        "format": {
                            "Description": {
                                "memberOf": {
                                    "@_resource": "http://purl.org/dc/terms/IMT"
                                },
                                "value": {
                                    "#text": "application/x-mobipocket-ebook",
                                    "@_datatype": "http://purl.org/dc/terms/IMT"
                                },
                                "@_nodeID": "Nf787662108444795a3035a5ac1968a45"
                            }
                        },
                        "@_about": "https://www.gutenberg.org/ebooks/11065.kindle.images"
                    }
                },
                {
                    "file": {
                        "isFormatOf": {
                            "@_resource": "ebooks/11065"
                        },
                        "extent": {
                            "#text": 90438,
                            "@_datatype": "http://www.w3.org/2001/XMLSchema#integer"
                        },
                        "modified": {
                            "#text": "2022-09-05T11:30:08.469754",
                            "@_datatype": "http://www.w3.org/2001/XMLSchema#dateTime"
                        },
                        "format": {
                            "Description": {
                                "memberOf": {
                                    "@_resource": "http://purl.org/dc/terms/IMT"
                                },
                                "value": {
                                    "#text": "application/x-mobipocket-ebook",
                                    "@_datatype": "http://purl.org/dc/terms/IMT"
                                },
                                "@_nodeID": "N56463e5b56654942a11ffa7cd148730a"
                            }
                        },
                        "@_about": "https://www.gutenberg.org/ebooks/11065.kindle.noimages"
                    }
                },
                {
                    "file": {
                        "isFormatOf": {
                            "@_resource": "ebooks/11065"
                        },
                        "extent": {
                            "#text": 1343594,
                            "@_datatype": "http://www.w3.org/2001/XMLSchema#integer"
                        },
                        "modified": {
                            "#text": "2022-09-05T11:30:11.450733",
                            "@_datatype": "http://www.w3.org/2001/XMLSchema#dateTime"
                        },
                        "format": {
                            "Description": {
                                "memberOf": {
                                    "@_resource": "http://purl.org/dc/terms/IMT"
                                },
                                "value": {
                                    "#text": "application/epub+zip",
                                    "@_datatype": "http://purl.org/dc/terms/IMT"
                                },
                                "@_nodeID": "N1f453501f9c24d09a213fa292eb6ea2f"
                            }
                        },
                        "@_about": "https://www.gutenberg.org/ebooks/11065.epub3.images"
                    }
                },
                {
                    "file": {
                        "isFormatOf": {
                            "@_resource": "ebooks/11065"
                        },
                        "extent": {
                            "#text": 1313904,
                            "@_datatype": "http://www.w3.org/2001/XMLSchema#integer"
                        },
                        "modified": {
                            "#text": "2022-09-05T11:30:12.867776",
                            "@_datatype": "http://www.w3.org/2001/XMLSchema#dateTime"
                        },
                        "format": {
                            "Description": {
                                "memberOf": {
                                    "@_resource": "http://purl.org/dc/terms/IMT"
                                },
                                "value": {
                                    "#text": "application/x-mobipocket-ebook",
                                    "@_datatype": "http://purl.org/dc/terms/IMT"
                                },
                                "@_nodeID": "N8b69d99327994b37bb1266294a0786e0"
                            }
                        },
                        "@_about": "https://www.gutenberg.org/ebooks/11065.kf8.images"
                    }
                },
                {
                    "file": {
                        "isFormatOf": {
                            "@_resource": "ebooks/11065"
                        },
                        "extent": {
                            "#text": 34550,
                            "@_datatype": "http://www.w3.org/2001/XMLSchema#integer"
                        },
                        "modified": {
                            "#text": "2022-09-05T11:30:06.779693",
                            "@_datatype": "http://www.w3.org/2001/XMLSchema#dateTime"
                        },
                        "format": {
                            "Description": {
                                "memberOf": {
                                    "@_resource": "http://purl.org/dc/terms/IMT"
                                },
                                "value": {
                                    "#text": "text/plain",
                                    "@_datatype": "http://purl.org/dc/terms/IMT"
                                },
                                "@_nodeID": "N126c61b9d777451994f4e86006a8b230"
                            }
                        },
                        "@_about": "https://www.gutenberg.org/ebooks/11065.txt.utf-8"
                    }
                },
                {
                    "file": {
                        "isFormatOf": {
                            "@_resource": "ebooks/11065"
                        },
                        "extent": {
                            "#text": 34571,
                            "@_datatype": "http://www.w3.org/2001/XMLSchema#integer"
                        },
                        "modified": {
                            "#text": "2004-02-12T23:44:15",
                            "@_datatype": "http://www.w3.org/2001/XMLSchema#dateTime"
                        },
                        "format": {
                            "Description": {
                                "memberOf": {
                                    "@_resource": "http://purl.org/dc/terms/IMT"
                                },
                                "value": {
                                    "#text": "text/plain; charset=us-ascii",
                                    "@_datatype": "http://purl.org/dc/terms/IMT"
                                },
                                "@_nodeID": "Na7e59ea4747144548842c765b5ff6386"
                            }
                        },
                        "@_about": "https://www.gutenberg.org/files/11065/11065.txt"
                    }
                },
                {
                    "file": {
                        "isFormatOf": {
                            "@_resource": "ebooks/11065"
                        },
                        "extent": {
                            "#text": 12752,
                            "@_datatype": "http://www.w3.org/2001/XMLSchema#integer"
                        },
                        "modified": {
                            "#text": "2004-02-12T23:44:15",
                            "@_datatype": "http://www.w3.org/2001/XMLSchema#dateTime"
                        },
                        "format": [
                            {
                                "Description": {
                                    "memberOf": {
                                        "@_resource": "http://purl.org/dc/terms/IMT"
                                    },
                                    "value": {
                                        "#text": "text/plain",
                                        "@_datatype": "http://purl.org/dc/terms/IMT"
                                    },
                                    "@_nodeID": "N17564dac807e4ee9bf3e31bcd2d0c1df"
                                }
                            },
                            {
                                "Description": {
                                    "memberOf": {
                                        "@_resource": "http://purl.org/dc/terms/IMT"
                                    },
                                    "value": {
                                        "#text": "application/zip",
                                        "@_datatype": "http://purl.org/dc/terms/IMT"
                                    },
                                    "@_nodeID": "Nd7b5d1374b924a0ab5024ac2dbb338fa"
                                }
                            }
                        ],
                        "@_about": "https://www.gutenberg.org/files/11065/11065.zip"
                    }
                },
                {
                    "file": {
                        "isFormatOf": {
                            "@_resource": "ebooks/11065"
                        },
                        "extent": {
                            "#text": 13590,
                            "@_datatype": "http://www.w3.org/2001/XMLSchema#integer"
                        },
                        "modified": {
                            "#text": "2022-09-05T11:30:13.003738",
                            "@_datatype": "http://www.w3.org/2001/XMLSchema#dateTime"
                        },
                        "format": {
                            "Description": {
                                "memberOf": {
                                    "@_resource": "http://purl.org/dc/terms/IMT"
                                },
                                "value": {
                                    "#text": "application/rdf+xml",
                                    "@_datatype": "http://purl.org/dc/terms/IMT"
                                },
                                "@_nodeID": "Nef3a1aff925d439b843a7ead50508fce"
                            }
                        },
                        "@_about": "https://www.gutenberg.org/ebooks/11065.rdf"
                    }
                },
                {
                    "file": {
                        "isFormatOf": {
                            "@_resource": "ebooks/11065"
                        },
                        "extent": {
                            "#text": 19035,
                            "@_datatype": "http://www.w3.org/2001/XMLSchema#integer"
                        },
                        "modified": {
                            "#text": "2022-09-05T11:30:08.582706",
                            "@_datatype": "http://www.w3.org/2001/XMLSchema#dateTime"
                        },
                        "format": {
                            "Description": {
                                "memberOf": {
                                    "@_resource": "http://purl.org/dc/terms/IMT"
                                },
                                "value": {
                                    "#text": "image/jpeg",
                                    "@_datatype": "http://purl.org/dc/terms/IMT"
                                },
                                "@_nodeID": "N34f7dbb99cc547ea8a22e567c36b4578"
                            }
                        },
                        "@_about": "https://www.gutenberg.org/cache/epub/11065/pg11065.cover.medium.jpg"
                    }
                },
                {
                    "file": {
                        "isFormatOf": {
                            "@_resource": "ebooks/11065"
                        },
                        "extent": {
                            "#text": 2775,
                            "@_datatype": "http://www.w3.org/2001/XMLSchema#integer"
                        },
                        "modified": {
                            "#text": "2022-09-05T11:30:08.546717",
                            "@_datatype": "http://www.w3.org/2001/XMLSchema#dateTime"
                        },
                        "format": {
                            "Description": {
                                "memberOf": {
                                    "@_resource": "http://purl.org/dc/terms/IMT"
                                },
                                "value": {
                                    "#text": "image/jpeg",
                                    "@_datatype": "http://purl.org/dc/terms/IMT"
                                },
                                "@_nodeID": "N9159c7b18a8e409e8e54a6eb4ac41969"
                            }
                        },
                        "@_about": "https://www.gutenberg.org/cache/epub/11065/pg11065.cover.small.jpg"
                    }
                }
            ],
            "@_about": "ebooks/11065"
        },
        "Description": [
            {
                "description": "More titles under Unknown",
                "@_about": "ebooks/author/49"
            },
            {
                "description": "en.wikipedia",
                "@_about": "https://en.wikipedia.org/wiki/Anonymous_work"
            }
        ],
        "@_base": "http://www.gutenberg.org/"
    }
}
