{
    "?xml": {
        "@_version": 1,
        "@_encoding": "utf-8"
    },
    "RDF": {
        "ebook": {
            "publisher": "Project Gutenberg",
            "license": {
                "@_resource": "license"
            },
            "issued": {
                "#text": "2004-05-01",
                "@_datatype": "http://www.w3.org/2001/XMLSchema#date"
            },
            "rights": "Public domain in the USA.",
            "downloads": {
                "#text": 30,
                "@_datatype": "http://www.w3.org/2001/XMLSchema#integer"
            },
            "creator": {
                "agent": {
                    "name": "Mommsen, Theodor",
                    "birthdate": {
                        "#text": 1817,
                        "@_datatype": "http://www.w3.org/2001/XMLSchema#integer"
                    },
                    "deathdate": {
                        "#text": 1903,
                        "@_datatype": "http://www.w3.org/2001/XMLSchema#integer"
                    },
                    "alias": [
                        "Mommsen, Christian Matthias Theodor",
                        "Mommsen, Theodorus",
                        "Mommzen, Teodor",
                        "Mommsen, T. (Theodor)",
                        "Mommsen, Teodoro"
                    ],
                    "webpage": [
                        {
                            "@_resource": "https://en.wikipedia.org/wiki/Theodor_Mommsen"
                        },
                        {
                            "@_resource": "https://de.wikipedia.org/wiki/Theodor_Mommsen"
                        }
                    ],
                    "@_about": "2009/agents/1105"
                }
            },
            "trl": {
                "agent": {
                    "name": "Dickson, William P. (William Purdie)",
                    "birthdate": {
                        "#text": 1823,
                        "@_datatype": "http://www.w3.org/2001/XMLSchema#integer"
                    },
                    "deathdate": {
                        "#text": 1901,
                        "@_datatype": "http://www.w3.org/2001/XMLSchema#integer"
                    },
                    "alias": "Dickson, William Purdie",
                    "@_about": "2009/agents/6282"
                }
            },
            "title": "The History of Rome, Book III&#13;\nFrom the Union of Italy to the Subjugation of Carthage and the Greek States",
            "language": {
                "Description": {
                    "value": {
                        "#text": "en",
                        "@_datatype": "http://purl.org/dc/terms/RFC4646"
                    },
                    "@_nodeID": "N38b33ecc878e4107b99033a2eb99e388"
                }
            },
            "subject": [
                {
                    "Description": {
                        "memberOf": {
                            "@_resource": "http://purl.org/dc/terms/LCSH"
                        },
                        "value": "Rome -- History",
                        "@_nodeID": "N3e60229a29a94238bccda8daaff2de00"
                    }
                },
                {
                    "Description": {
                        "memberOf": {
                            "@_resource": "http://purl.org/dc/terms/LCC"
                        },
                        "value": "DG",
                        "@_nodeID": "Ne57866d96bba46f8916a9f65b94db970"
                    }
                }
            ],
            "hasFormat": [
                {
                    "file": {
                        "isFormatOf": {
                            "@_resource": "ebooks/10703"
                        },
                        "extent": {
                            "#text": 1291836,
                            "@_datatype": "http://www.w3.org/2001/XMLSchema#integer"
                        },
                        "modified": {
                            "#text": "2022-09-05T09:31:16.839869",
                            "@_datatype": "http://www.w3.org/2001/XMLSchema#dateTime"
                        },
                        "format": {
                            "Description": {
                                "memberOf": {
                                    "@_resource": "http://purl.org/dc/terms/IMT"
                                },
                                "value": {
                                    "#text": "text/html",
                                    "@_datatype": "http://purl.org/dc/terms/IMT"
                                },
                                "@_nodeID": "N34fe4746975a48a8b381e5cdc83dcd6e"
                            }
                        },
                        "@_about": "https://www.gutenberg.org/ebooks/10703.html.images"
                    }
                },
                {
                    "file": {
                        "isFormatOf": {
                            "@_resource": "ebooks/10703"
                        },
                        "extent": {
                            "#text": 1291829,
                            "@_datatype": "http://www.w3.org/2001/XMLSchema#integer"
                        },
                        "modified": {
                            "#text": "2022-09-05T09:31:17.018886",
                            "@_datatype": "http://www.w3.org/2001/XMLSchema#dateTime"
                        },
                        "format": {
                            "Description": {
                                "memberOf": {
                                    "@_resource": "http://purl.org/dc/terms/IMT"
                                },
                                "value": {
                                    "#text": "text/html",
                                    "@_datatype": "http://purl.org/dc/terms/IMT"
                                },
                                "@_nodeID": "Nff4b6efa84b84083abeae2679058a956"
                            }
                        },
                        "@_about": "https://www.gutenberg.org/ebooks/10703.html.noimages"
                    }
                },
                {
                    "file": {
                        "isFormatOf": {
                            "@_resource": "ebooks/10703"
                        },
                        "extent": {
                            "#text": 559560,
                            "@_datatype": "http://www.w3.org/2001/XMLSchema#integer"
                        },
                        "modified": {
                            "#text": "2022-09-05T09:31:27.202995",
                            "@_datatype": "http://www.w3.org/2001/XMLSchema#dateTime"
                        },
                        "format": {
                            "Description": {
                                "memberOf": {
                                    "@_resource": "http://purl.org/dc/terms/IMT"
                                },
                                "value": {
                                    "#text": "application/epub+zip",
                                    "@_datatype": "http://purl.org/dc/terms/IMT"
                                },
                                "@_nodeID": "N346c0b2e50c84c2db266a16b528d9cb0"
                            }
                        },
                        "@_about": "https://www.gutenberg.org/ebooks/10703.epub.images"
                    }
                },
                {
                    "file": {
                        "isFormatOf": {
                            "@_resource": "ebooks/10703"
                        },
                        "extent": {
                            "#text": 559560,
                            "@_datatype": "http://www.w3.org/2001/XMLSchema#integer"
                        },
                        "modified": {
                            "#text": "2022-09-05T09:31:17.595907",
                            "@_datatype": "http://www.w3.org/2001/XMLSchema#dateTime"
                        },
                        "format": {
                            "Description": {
                                "memberOf": {
                                    "@_resource": "http://purl.org/dc/terms/IMT"
                                },
                                "value": {
                                    "#text": "application/epub+zip",
                                    "@_datatype": "http://purl.org/dc/terms/IMT"
                                },
                                "@_nodeID": "N8315696deff040629ae10424b064718b"
                            }
                        },
                        "@_about": "https://www.gutenberg.org/ebooks/10703.epub.noimages"
                    }
                },
                {
                    "file": {
                        "isFormatOf": {
                            "@_resource": "ebooks/10703"
                        },
                        "extent": {
                            "#text": 869192,
                            "@_datatype": "http://www.w3.org/2001/XMLSchema#integer"
                        },
                        "modified": {
                            "#text": "2022-09-05T09:31:35.881022",
                            "@_datatype": "http://www.w3.org/2001/XMLSchema#dateTime"
                        },
                        "format": {
                            "Description": {
                                "memberOf": {
                                    "@_resource": "http://purl.org/dc/terms/IMT"
                                },
                                "value": {
                                    "#text": "application/x-mobipocket-ebook",
                                    "@_datatype": "http://purl.org/dc/terms/IMT"
                                },
                                "@_nodeID": "N7a657d7aacf543548c26178e4351694b"
                            }
                        },
                        "@_about": "https://www.gutenberg.org/ebooks/10703.kindle.images"
                    }
                },
                {
                    "file": {
                        "isFormatOf": {
                            "@_resource": "ebooks/10703"
                        },
                        "extent": {
                            "#text": 869192,
                            "@_datatype": "http://www.w3.org/2001/XMLSchema#integer"
                        },
                        "modified": {
                            "#text": "2022-09-05T09:31:26.266955",
                            "@_datatype": "http://www.w3.org/2001/XMLSchema#dateTime"
                        },
                        "format": {
                            "Description": {
                                "memberOf": {
                                    "@_resource": "http://purl.org/dc/terms/IMT"
                                },
                                "value": {
                                    "#text": "application/x-mobipocket-ebook",
                                    "@_datatype": "http://purl.org/dc/terms/IMT"
                                },
                                "@_nodeID": "N40ba35e33f0b4fe2b5ed9bc57302f402"
                            }
                        },
                        "@_about": "https://www.gutenberg.org/ebooks/10703.kindle.noimages"
                    }
                },
                {
                    "file": {
                        "isFormatOf": {
                            "@_resource": "ebooks/10703"
                        },
                        "extent": {
                            "#text": 537780,
                            "@_datatype": "http://www.w3.org/2001/XMLSchema#integer"
                        },
                        "modified": {
                            "#text": "2022-09-05T09:31:36.447041",
                            "@_datatype": "http://www.w3.org/2001/XMLSchema#dateTime"
                        },
                        "format": {
                            "Description": {
                                "memberOf": {
                                    "@_resource": "http://purl.org/dc/terms/IMT"
                                },
                                "value": {
                                    "#text": "application/epub+zip",
                                    "@_datatype": "http://purl.org/dc/terms/IMT"
                                },
                                "@_nodeID": "N699f909740b844edb6feb802e9e4ce71"
                            }
                        },
                        "@_about": "https://www.gutenberg.org/ebooks/10703.epub3.images"
                    }
                },
                {
                    "file": {
                        "isFormatOf": {
                            "@_resource": "ebooks/10703"
                        },
                        "extent": {
                            "#text": 920150,
                            "@_datatype": "http://www.w3.org/2001/XMLSchema#integer"
                        },
                        "modified": {
                            "#text": "2022-09-05T09:31:44.704122",
                            "@_datatype": "http://www.w3.org/2001/XMLSchema#dateTime"
                        },
                        "format": {
                            "Description": {
                                "memberOf": {
                                    "@_resource": "http://purl.org/dc/terms/IMT"
                                },
                                "value": {
                                    "#text": "application/x-mobipocket-ebook",
                                    "@_datatype": "http://purl.org/dc/terms/IMT"
                                },
                                "@_nodeID": "N64e2f55aa992486fba6291a22268e0cf"
                            }
                        },
                        "@_about": "https://www.gutenberg.org/ebooks/10703.kf8.images"
                    }
                },
                {
                    "file": {
                        "isFormatOf": {
                            "@_resource": "ebooks/10703"
                        },
                        "extent": {
                            "#text": 1252943,
                            "@_datatype": "http://www.w3.org/2001/XMLSchema#integer"
                        },
                        "modified": {
                            "#text": "2022-09-05T09:31:16.317895",
                            "@_datatype": "http://www.w3.org/2001/XMLSchema#dateTime"
                        },
                        "format": {
                            "Description": {
                                "memberOf": {
                                    "@_resource": "http://purl.org/dc/terms/IMT"
                                },
                                "value": {
                                    "#text": "text/plain",
                                    "@_datatype": "http://purl.org/dc/terms/IMT"
                                },
                                "@_nodeID": "Na1b8c7f989dd478ba2202c4b20fad015"
                            }
                        },
                        "@_about": "https://www.gutenberg.org/ebooks/10703.txt.utf-8"
                    }
                },
                {
                    "file": {
                        "isFormatOf": {
                            "@_resource": "ebooks/10703"
                        },
                        "extent": {
                            "#text": 1252976,
                            "@_datatype": "http://www.w3.org/2001/XMLSchema#integer"
                        },
                        "modified": {
                            "#text": "2020-12-20T03:40:31",
                            "@_datatype": "http://www.w3.org/2001/XMLSchema#dateTime"
                        },
                        "format": {
                            "Description": {
                                "memberOf": {
                                    "@_resource": "http://purl.org/dc/terms/IMT"
                                },
                                "value": {
                                    "#text": "text/plain; charset=us-ascii",
                                    "@_datatype": "http://purl.org/dc/terms/IMT"
                                },
                                "@_nodeID": "Nd69f0d6d0ce449999317cc33050a1f30"
                            }
                        },
                        "@_about": "https://www.gutenberg.org/files/10703/10703.txt"
                    }
                },
                {
                    "file": {
                        "isFormatOf": {
                            "@_resource": "ebooks/10703"
                        },
                        "extent": {
                            "#text": 458666,
                            "@_datatype": "http://www.w3.org/2001/XMLSchema#integer"
                        },
                        "modified": {
                            "#text": "2020-12-20T03:40:31",
                            "@_datatype": "http://www.w3.org/2001/XMLSchema#dateTime"
                        },
                        "format": [
                            {
                                "Description": {
                                    "memberOf": {
                                        "@_resource": "http://purl.org/dc/terms/IMT"
                                    },
                                    "value": {
                                        "#text": "text/plain; charset=us-ascii",
                                        "@_datatype": "http://purl.org/dc/terms/IMT"
                                    },
                                    "@_nodeID": "N6d3301a9f2b94743978153963e00fc98"
                                }
                            },
                            {
                                "Description": {
                                    "memberOf": {
                                        "@_resource": "http://purl.org/dc/terms/IMT"
                                    },
                                    "value": {
                                        "#text": "application/zip",
                                        "@_datatype": "http://purl.org/dc/terms/IMT"
                                    },
                                    "@_nodeID": "Nda24aeddc1b0441593e9f1f947f1aec4"
                                }
                            }
                        ],
                        "@_about": "https://www.gutenberg.org/files/10703/10703.zip"
                    }
                },
                {
                    "file": {
                        "isFormatOf": {
                            "@_resource": "ebooks/10703"
                        },
                        "extent": {
                            "#text": 13343,
                            "@_datatype": "http://www.w3.org/2001/XMLSchema#integer"
                        },
                        "modified": {
                            "#text": "2022-09-05T09:31:44.841093",
                            "@_datatype": "http://www.w3.org/2001/XMLSchema#dateTime"
                        },
                        "format": {
                            "Description": {
                                "memberOf": {
                                    "@_resource": "http://purl.org/dc/terms/IMT"
                                },
                                "value": {
                                    "#text": "application/rdf+xml",
                                    "@_datatype": "http://purl.org/dc/terms/IMT"
                                },
                                "@_nodeID": "Ne3c28f4f2baa46389ca714b411a67757"
                            }
                        },
                        "@_about": "https://www.gutenberg.org/ebooks/10703.rdf"
                    }
                },
                {
                    "file": {
                        "isFormatOf": {
                            "@_resource": "ebooks/10703"
                        },
                        "extent": {
                            "#text": 14990,
                            "@_datatype": "http://www.w3.org/2001/XMLSchema#integer"
                        },
                        "modified": {
                            "#text": "2022-09-05T09:31:26.636952",
                            "@_datatype": "http://www.w3.org/2001/XMLSchema#dateTime"
                        },
                        "format": {
                            "Description": {
                                "memberOf": {
                                    "@_resource": "http://purl.org/dc/terms/IMT"
                                },
                                "value": {
                                    "#text": "image/jpeg",
                                    "@_datatype": "http://purl.org/dc/terms/IMT"
                                },
                                "@_nodeID": "N1b16ebb269d84c5480e141ca62f557d2"
                            }
                        },
                        "@_about": "https://www.gutenberg.org/cache/epub/10703/pg10703.cover.medium.jpg"
                    }
                },
                {
                    "file": {
                        "isFormatOf": {
                            "@_resource": "ebooks/10703"
                        },
                        "extent": {
                            "#text": 3303,
                            "@_datatype": "http://www.w3.org/2001/XMLSchema#integer"
                        },
                        "modified": {
                            "#text": "2022-09-05T09:31:26.474954",
                            "@_datatype": "http://www.w3.org/2001/XMLSchema#dateTime"
                        },
                        "format": {
                            "Description": {
                                "memberOf": {
                                    "@_resource": "http://purl.org/dc/terms/IMT"
                                },
                                "value": {
                                    "#text": "image/jpeg",
                                    "@_datatype": "http://purl.org/dc/terms/IMT"
                                },
                                "@_nodeID": "N6d1be5eedd224245a1321757463dca18"
                            }
                        },
                        "@_about": "https://www.gutenberg.org/cache/epub/10703/pg10703.cover.small.jpg"
                    }
                }
            ],
            "@_about": "ebooks/10703"
        },
        "Work": {
            "license": {
                "@_resource": "https://creativecommons.org/publicdomain/zero/1.0/"
            },
            "comment": "Archives containing the RDF files for *all* our books can be downloaded at\n            https://www.gutenberg.org/wiki/Gutenberg:Feeds#The_Complete_Project_Gutenberg_Catalog",
            "@_about": ""
        },
        "Description": [
            {
                "description": "de.wikipedia",
                "@_about": "https://de.wikipedia.org/wiki/Theodor_Mommsen"
            },
            {
                "description": "en.wikipedia",
                "@_about": "https://en.wikipedia.org/wiki/Theodor_Mommsen"
            }
        ],
        "@_base": "http://www.gutenberg.org/"
    }
}
